space_mining/__init__.py
space_mining/agents/__init__.py
space_mining/agents/callbacks.py
space_mining/agents/ppo_agent.py
space_mining/agents/train_ppo.py
space_mining/envs/__init__.py
space_mining/envs/renderer.py
space_mining/envs/space_mining.py
space_mining/envs/wrappers.py
space_mining/scripts/make_gif.py
space_mining/scripts/render_episode.py
space_mining-0.1.2.dist-info/LICENSE
space_mining-0.1.2.dist-info/METADATA
space_mining-0.1.2.dist-info/WHEEL
space_mining-0.1.2.dist-info/RECORD
