Metadata-Version: 2.3
Name: space-mining
Version: 0.1.2
Summary: A Gymnasium-compatible environment for space mining reinforcement learning tasks
License: MIT
Author: Xinning Zhu
Author-email: zhuxinning@shu.edu.cn
Requires-Python: >=3.10,<4.0
Classifier: License :: OSI Approved :: MIT License
Classifier: Operating System :: OS Independent
Classifier: Programming Language :: Python :: 3
Classifier: Programming Language :: Python :: 3.10
Classifier: Programming Language :: Python :: 3.11
Classifier: Programming Language :: Python :: 3.12
Classifier: Programming Language :: Python :: 3.13
Classifier: Programming Language :: Python :: 3 :: Only
Requires-Dist: gymnasium (>=0.29.1,<0.30.0)
Requires-Dist: numpy (>=1.23.0,<2.0.0)
Requires-Dist: pygame (>=2.5.2,<3.0.0)
Requires-Dist: stable-baselines3 (>=2.0.0,<3.0.0)
